[{"url": "https://www.kuaishou.com/short-video/3xxv5b6vd9jtk9m", "title": "中央定调2026年经济工作"}, {"url": "https://www.kuaishou.com/short-video/3xp9rda23cq5tnc", "title": "第十二个国家公祭日"}, {"url": "https://www.kuaishou.com/short-video/3x49eqdrxuh978e", "title": "南京大屠杀真实影像"}, {"url": "https://www.kuaishou.com/short-video/3xfa8nygvaetjiw", "title": "2026年如何有效提振消费"}, {"url": "https://www.kuaishou.com/short-video/3xc3xcawkysveya", "title": "北京初雪就是中式美学天花板"}, {"url": "https://www.kuaishou.com/short-video/3xyqcuiiu4e6tyi", "title": "警惕日本谋划“太空珍珠港事件”"}, {"url": "https://www.kuaishou.com/short-video/3xdc9kbz34hb9xi", "title": "柬埔寨称泰军向境内投掷数枚炸弹"}, {"url": "https://www.kuaishou.com/short-video/3xrhp7y97288u9i", "title": "均价500元的手机壳被吐槽质量差"}, {"url": "https://www.kuaishou.com/short-video/3xua8ptiihg3cp6", "title": "专家谈日本九州集结两栖作战部队"}, {"url": "https://www.kuaishou.com/short-video/3x5wg2fkpu3wyfs", "title": "80秒看懂中央经济工作会议"}, {"url": "https://www.kuaishou.com/short-video/3xtu8v7e4gbdr9k", "title": "去年夏天手势舞"}, {"url": "https://www.kuaishou.com/short-video/3x6423d3vvegdzk", "title": "这一句道歉我们已经等了88年"}, {"url": "https://www.kuaishou.com/short-video/3xbwjwqgjeu4xcm", "title": "英国国王称癌症治疗进展良好"}, {"url": "https://www.kuaishou.com/short-video/3xtp3ttbd3zjui6", "title": "南京大屠杀为何发生"}, {"url": "https://www.kuaishou.com/short-video/3xsefw5vj5m2n62", "title": "转职山东人是什么梗"}, {"url": "https://www.kuaishou.com/short-video/3x23uz8stx33rqa", "title": "阿里噶多猫耳舞"}, {"url": "https://www.kuaishou.com/short-video/3xfd9ivbcxtbyw4", "title": "拒绝XX羞耻是什么梗"}, {"url": "https://www.kuaishou.com/short-video/3x66gwtt64e3u2e", "title": "假新闻里的和睦真镜头下的暴行"}, {"url": "https://www.kuaishou.com/short-video/3x78hnsp5ihmsrg", "title": "孙颖莎晋级WTT香港总决赛四强"}, {"url": "https://www.kuaishou.com/short-video/3xa2x3f3y7v7ihm", "title": "哈登称火箭队阵容非常好"}, {"url": "https://www.kuaishou.com/short-video/3x7vvbkesrc66ks", "title": "爱人的眼睛像一只蓝鸟"}, {"url": "https://www.kuaishou.com/short-video/3xibgtbvnprpufg", "title": "今年8位南京大屠杀幸存者离世"}, {"url": "https://www.kuaishou.com/short-video/3xuuwarzeu49jri", "title": "张继科回应王曼昱实力"}, {"url": "https://www.kuaishou.com/short-video/3xhgekmx3qbhva2", "title": "成都地震"}, {"url": "https://www.kuaishou.com/short-video/3x73r9mndv9ikqg", "title": "全选C的试卷被学走了"}, {"url": "https://www.kuaishou.com/short-video/3xewvtzwr35b88e", "title": "今天的南京城有30多万人要回家"}, {"url": "https://www.kuaishou.com/short-video/3xcqwzqmbb3ckxi", "title": "官方出手整治大字吸睛小字免责"}, {"url": "https://www.kuaishou.com/short-video/3xafkt8jevpaeg6", "title": "御姐摇"}, {"url": "https://www.kuaishou.com/short-video/3xpfjctjvn2dcn4", "title": "驻以使馆回应台湾官员窜访以色列"}, {"url": "https://www.kuaishou.com/short-video/3xev8xdr9759ray", "title": "无痛淋巴结肿大需警惕"}, {"url": "https://www.kuaishou.com/short-video/3x8r9ya68peffb2", "title": "“微笑抑郁症”需警惕"}, {"url": "https://www.kuaishou.com/short-video/3x84ujmzk7hjcqq", "title": "虞书欣争议缠身未回应"}, {"url": "https://www.kuaishou.com/short-video/3xjbwhgxwgp884w", "title": "南京舰守护今日南京"}, {"url": "https://www.kuaishou.com/short-video/3x6wkzwncy6sxqw", "title": "2025年最暖心的梗出现了"}, {"url": "https://www.kuaishou.com/short-video/3xtzc6c9mt3up4g", "title": "下雪的哈尔滨翻唱"}, {"url": "https://www.kuaishou.com/short-video/3xm8bssqm8ubbh6", "title": "老婆最棒手势舞"}, {"url": "https://www.kuaishou.com/short-video/3xg2jv7qcn2i334", "title": "今天请为他们停留一分钟"}, {"url": "https://www.kuaishou.com/short-video/3x5etrw4jkxphk2", "title": "十二月就这样对我王者版"}, {"url": "https://www.kuaishou.com/short-video/3xqzfgx7n6fpmv2", "title": "新能源车为何修不起"}, {"url": "https://www.kuaishou.com/short-video/3xffezhqfgzgp66", "title": "南方人玩雪 北方人玩南方人"}, {"url": "https://www.kuaishou.com/short-video/3x6rcenrpwr37sy", "title": "东京审判法官后人南昌相聚"}, {"url": "https://www.kuaishou.com/short-video/3xre7kzkkg8vb9i", "title": "鸡蛋仙人vs米饭仙人"}, {"url": "https://www.kuaishou.com/short-video/3xewrhc2bvp6n9w", "title": "美国死刑犯行刑前吃高热量食物"}, {"url": "https://www.kuaishou.com/short-video/3x82qecjn9i2u7w", "title": "雪花雪花你可听见翻唱"}, {"url": "https://www.kuaishou.com/short-video/3xqvgiztny6x4iu", "title": "让军国主义如过街老鼠无处遁形"}, {"url": "https://www.kuaishou.com/short-video/3xejbpcfxs8efeg", "title": "远赴北平 畅听游京"}, {"url": "https://www.kuaishou.com/short-video/3x3yx8vp2uyusam", "title": "公牛vs黄蜂"}, {"url": "https://www.kuaishou.com/short-video/3xqyp9d59xgsk9a", "title": "台北下了雪舞蹈挑战"}]